aio2ch/__init__.py
aio2ch/__version__.py
aio2ch/_api.py
aio2ch/_api_client.py
aio2ch/_exceptions.py
aio2ch/_helpers.py
aio2ch/_objects.py
aio2ch/cli/__init__.py
aio2ch/cli/download.py
aio2ch-3.2.1.dist-info/LICENSE
aio2ch-3.2.1.dist-info/METADATA
aio2ch-3.2.1.dist-info/WHEEL
aio2ch-3.2.1.dist-info/entry_points.txt
aio2ch-3.2.1.dist-info/top_level.txt
aio2ch-3.2.1.dist-info/RECORD
