Metadata-Version: 2.1
Name: aio2ch
Version: 3.2.1
Summary: Fully asynchronous read-only API wrapper for 2ch.hk (dvach)
Home-page: https://github.com/wkpn/aio2ch
Author: wkpn
License: MIT
Keywords: 2ch,Двач,Dvach,api,wrapper,async
Platform: UNKNOWN
Classifier: Development Status :: 5 - Production/Stable
Classifier: Framework :: AsyncIO
Classifier: Intended Audience :: Developers
Classifier: License :: OSI Approved :: MIT License
Classifier: Programming Language :: Python :: 3.6
Classifier: Programming Language :: Python :: 3.7
Classifier: Programming Language :: Python :: 3.8
Classifier: Programming Language :: Python :: 3.9
Requires-Python: >=3.6
Requires-Dist: httpx[http2] (==0.17.0)
Requires-Dist: aiofiles (==0.6.0)
Requires-Dist: click
